pyhfcorr/__init__.py
pyhfcorr/decorrelate.py
pyhfcorr/modifiers.py
pyhfcorr-0.1.dev39.dist-info/METADATA
pyhfcorr-0.1.dev39.dist-info/WHEEL
pyhfcorr-0.1.dev39.dist-info/licenses/LICENSE
pyhfcorr-0.1.dev39.dist-info/RECORD
