Metadata-Version: 2.3
Name: pyhfcorr
Version: 0.1.dev39
Summary: Extension to pyhf for correlated uncertainties
Project-URL: Homepage, https://github.com/lorenzennio/pyhf-corr
Project-URL: Documentation, https://github.com/lorenzennio/pyhf-corr
Project-URL: Issue Tracker, https://github.com/lorenzennio/pyhf-corr/issues
Author-email: Lorenz Gaertner <lorenz.gaertner@gmail.com>
Maintainer-email: Lorenz Gaertner <lorenz.gaertner@gmail.com>
License: MIT
Classifier: Development Status :: 4 - Beta
Classifier: License :: OSI Approved :: MIT License
Classifier: Programming Language :: Python :: 3 :: Only
Classifier: Programming Language :: Python :: 3.8
Classifier: Programming Language :: Python :: 3.9
Classifier: Programming Language :: Python :: 3.10
Classifier: Programming Language :: Python :: 3.11
Classifier: Topic :: Scientific/Engineering :: Physics
Requires-Python: >=3.8
Requires-Dist: iminuit
Requires-Dist: ipykernel
Requires-Dist: jsonschema
Requires-Dist: matplotlib
Requires-Dist: numexpr
Requires-Dist: numpy
Requires-Dist: pip>=23.0
Requires-Dist: pre-commit
Requires-Dist: pyhf
Requires-Dist: pytest
Requires-Dist: requests
